CwnSenseTagger/__init__.py
CwnSenseTagger/config.py
CwnSenseTagger/cwn_annot_types.py
CwnSenseTagger/cwn_base.py
CwnSenseTagger/cwn_graph_utils.py
CwnSenseTagger/cwn_node_types.py
CwnSenseTagger/cwn_relation_types.py
CwnSenseTagger/cwn_types.py
CwnSenseTagger/download.py
CwnSenseTagger/model.py
CwnSenseTagger/preprocess.py
CwnSenseTagger/test.py
CwnSenseTagger/tokenize_test.py
CwnSenseTagger/util.py
CwnSenseTagger/wsd.py
CwnSenseTagger-0.1.6.dist-info/LICENSE
CwnSenseTagger-0.1.6.dist-info/METADATA
CwnSenseTagger-0.1.6.dist-info/WHEEL
CwnSenseTagger-0.1.6.dist-info/top_level.txt
CwnSenseTagger-0.1.6.dist-info/RECORD
