Metadata-Version: 2.1
Name: CwnSenseTagger
Version: 0.1.6
Summary: A package to use chinese word net to achieve word sense disambigution task
Home-page: UNKNOWN
Author: NTUGIL LOPE Lab
License: UNKNOWN
Platform: UNKNOWN
Classifier: Programming Language :: Python :: 3
Classifier: Operating System :: OS Independent
Requires-Python: >=3.5
Requires-Dist: numpy
Requires-Dist: pandas
Requires-Dist: torch (>=1.6)
Requires-Dist: tqdm
Requires-Dist: transformers (>=3.2)
